{"version": "0.2.4", "img_width": 841, "img_height": 1200, "blocks": [{"box": [244, 505, 289, 601], "vertical": true, "font_size": 20, "lines_coords": [[[268.0, 505.0], [288.0, 505.0], [288.0, 601.0], [268.0, 601.0]], [[244.0, 506.0], [264.0, 506.0], [264.0, 584.0], [244.0, 584.0]]], "lines": ["どうしたの", "かしら？"]}, {"box": [201, 746, 282, 930], "vertical": true, "font_size": 23, "lines_coords": [[[261.0, 748.0], [281.0, 748.0], [281.0, 930.0], [261.0, 930.0]], [[226.0, 746.0], [255.0, 746.0], [255.0, 819.0], [226.0, 819.0]], [[201.0, 747.0], [222.0, 747.0], [223.0, 885.0], [202.0, 885.0]]], "lines": ["もうちょっとらけ", "ここに", "かくれてよう"]}, {"box": [69, 1142, 384, 1177], "vertical": false, "font_size": 17, "lines_coords": [[[283.0, 1149.0], [379.0, 1151.0], [379.0, 1173.0], [283.0, 1170.0]], [[78.0, 1158.0], [122.0, 1156.0], [122.0, 1169.0], [78.0, 1171.0]]], "lines": ["終わり", "．．"]}]}