{"version": "0.2.4", "img_width": 841, "img_height": 1200, "blocks": [{"box": [86, 94, 590, 146], "vertical": false, "font_size": 29, "lines_coords": [[[96.0, 111.0], [258.0, 109.0], [258.0, 129.0], [96.0, 132.0]], [[339.0, 99.0], [586.0, 99.0], [586.0, 140.0], [339.0, 140.0]]], "lines": ["ｈｏｍｅ．ｍａｄｅ", "猫、思い出す。"]}, {"box": [114, 717, 201, 740], "vertical": false, "font_size": 20, "lines_coords": [[[115.0, 717.0], [201.0, 720.0], [200.0, 740.0], [114.0, 737.0]]], "lines": ["．．．って"]}, {"box": [487, 793, 516, 864], "vertical": true, "font_size": 29, "lines_coords": [[[487.0, 793.0], [516.0, 793.0], [516.0, 864.0], [487.0, 864.0]]], "lines": ["みゃっ"]}, {"box": [718, 829, 743, 896], "vertical": true, "font_size": 25, "lines_coords": [[[718.0, 829.0], [743.0, 829.0], [743.0, 896.0], [718.0, 896.0]]], "lines": ["フーン"]}]}