{"version": "0.2.4", "img_width": 841, "img_height": 1200, "blocks": [{"box": [775, 185, 797, 206], "vertical": true, "font_size": 23, "lines_coords": [[[775.0, 185.0], [797.0, 185.0], [797.0, 206.0], [775.0, 206.0]]], "lines": ["あ"]}, {"box": [729, 210, 755, 253], "vertical": true, "font_size": 23, "lines_coords": [[[729.0, 212.0], [753.0, 210.0], [755.0, 251.0], [732.0, 253.0]]], "lines": ["いえ"]}, {"box": [680, 191, 703, 234], "vertical": true, "font_size": 23, "lines_coords": [[[680.0, 191.0], [703.0, 191.0], [703.0, 234.0], [680.0, 234.0]]], "lines": ["まあ"]}, {"box": [579, 67, 624, 156], "vertical": true, "font_size": 18, "lines_coords": [[[604.0, 67.0], [624.0, 67.0], [624.0, 155.0], [604.0, 155.0]], [[582.0, 67.0], [598.0, 67.0], [596.0, 155.0], [579.0, 155.0]]], "lines": ["おそろいで", "お出かけ？"]}, {"box": [430, 98, 449, 193], "vertical": true, "font_size": 16, "lines_coords": [[[431.0, 98.0], [447.0, 98.0], [447.0, 192.0], [431.0, 192.0]]], "lines": ["いいわねえ"]}, {"box": [334, 113, 358, 135], "vertical": true, "font_size": 26, "lines_coords": [[[334.0, 113.0], [358.0, 113.0], [358.0, 135.0], [334.0, 135.0]]], "lines": ["あ"]}, {"box": [253, 111, 303, 195], "vertical": true, "font_size": 26, "lines_coords": [[[271.0, 112.0], [301.0, 111.0], [303.0, 194.0], [274.0, 195.0]], [[253.0, 112.0], [277.0, 112.0], [277.0, 194.0], [253.0, 194.0]]], "lines": ["いい天気", "ですねー"]}, {"box": [183, 87, 208, 150], "vertical": true, "font_size": 26, "lines_coords": [[[183.0, 87.0], [208.0, 87.0], [208.0, 150.0], [183.0, 150.0]]], "lines": ["ホホホ"]}, {"box": [728, 408, 802, 489], "vertical": true, "font_size": 21, "lines_coords": [[[775.0, 408.0], [802.0, 408.0], [802.0, 453.0], [775.0, 453.0]], [[749.0, 411.0], [770.0, 411.0], [770.0, 489.0], [749.0, 489.0]], [[728.0, 411.0], [744.0, 411.0], [744.0, 471.0], [728.0, 471.0]]], "lines": ["でも", "下り坂だ", "そうよ"]}, {"box": [475, 413, 541, 494], "vertical": true, "font_size": 23, "lines_coords": [[[521.0, 417.0], [541.0, 417.0], [541.0, 494.0], [521.0, 494.0]], [[493.0, 413.0], [522.0, 413.0], [522.0, 478.0], [493.0, 478.0]], [[475.0, 416.0], [496.0, 416.0], [496.0, 492.0], [475.0, 492.0]]], "lines": ["そーなん", "ですか", "ホホ．．．"]}, {"box": [212, 685, 229, 732], "vertical": true, "font_size": 17, "lines_coords": [[[212.0, 685.0], [229.0, 685.0], [229.0, 732.0], [212.0, 732.0]]], "lines": ["！"]}]}