{"version": "0.2.4", "img_width": 1505, "img_height": 2188, "blocks": [{"box": [880, 185, 932, 346], "vertical": true, "font_size": 52, "lines_coords": [[[880.0, 185.0], [932.0, 185.0], [932.0, 269.0], [880.0, 269.0]]], "lines": ["おー"]}, {"box": [579, 162, 619, 401], "vertical": true, "font_size": 36, "lines_coords": [[[579.0, 162.0], [615.0, 162.0], [617.0, 401.0], [581.0, 401.0]]], "lines": ["もうすぐだぞー"]}, {"box": [1353, 732, 1436, 940], "vertical": true, "font_size": 79, "lines_coords": [[[1357.0, 732.0], [1436.0, 735.0], [1432.0, 940.0], [1353.0, 938.0]]], "lines": ["よつば"]}, {"box": [542, 722, 1165, 1059], "vertical": false, "font_size": 324, "lines_coords": [[[549.0, 722.0], [1165.0, 735.0], [1158.0, 1059.0], [542.0, 1046.0]]], "lines": ["．．．"]}, {"box": [250, 741, 354, 1194], "vertical": true, "font_size": 92, "lines_coords": [[[269.0, 995.0], [348.0, 997.0], [342.0, 1194.0], [262.0, 1192.0]], [[250.0, 741.0], [354.0, 741.0], [354.0, 878.0], [250.0, 878.0]]], "lines": ["っ！！", "おー"]}, {"box": [1333, 1448, 1395, 1600], "vertical": true, "font_size": 62, "lines_coords": [[[1333.0, 1448.0], [1395.0, 1448.0], [1395.0, 1600.0], [1333.0, 1600.0]]], "lines": ["すげえ"]}, {"box": [1135, 1440, 1267, 1709], "vertical": true, "font_size": 37, "lines_coords": [[[1229.0, 1440.0], [1267.0, 1440.0], [1267.0, 1613.0], [1229.0, 1613.0]], [[1177.0, 1440.0], [1214.0, 1440.0], [1214.0, 1709.0], [1177.0, 1709.0]], [[1135.0, 1440.0], [1171.0, 1440.0], [1171.0, 1579.0], [1135.0, 1579.0]]], "lines": ["とーちゃん", "ここ家がいっぱい", "あるな！"]}, {"box": [1045, 1743, 1133, 1980], "vertical": true, "font_size": 34, "lines_coords": [[[1096.0, 1743.0], [1133.0, 1743.0], [1133.0, 1916.0], [1096.0, 1916.0]], [[1047.0, 1745.0], [1077.0, 1745.0], [1077.0, 1978.0], [1047.0, 1978.0]]], "lines": ["そーだろー", "お店もあるぞー"]}, {"box": [812, 1826, 872, 2029], "vertical": true, "font_size": 38, "lines_coords": [[[814.0, 1826.0], [852.0, 1826.0], [852.0, 2029.0], [814.0, 2029.0]]], "lines": ["お店もか！？"]}]}