{"version": "0.2.4", "img_width": 1505, "img_height": 2188, "blocks": [{"box": [882, 192, 929, 286], "vertical": true, "font_size": 47, "lines_coords": [[[882.0, 192.0], [929.0, 192.0], [929.0, 286.0], [882.0, 286.0]]], "lines": ["こう"]}, {"box": [523, 175, 622, 382], "vertical": true, "font_size": 45, "lines_coords": [[[570.0, 177.0], [615.0, 175.0], [622.0, 380.0], [577.0, 382.0]], [[523.0, 177.0], [568.0, 177.0], [568.0, 341.0], [523.0, 341.0]]], "lines": ["こうやって", "あそぶの"]}, {"box": [277, 164, 335, 226], "vertical": true, "font_size": 58, "lines_coords": [[[277.0, 164.0], [335.0, 164.0], [335.0, 226.0], [277.0, 226.0]]], "lines": ["お"]}, {"box": [104, 176, 190, 640], "vertical": true, "font_size": 66, "lines_coords": [[[128.0, 482.0], [175.0, 482.0], [175.0, 613.0], [128.0, 613.0]], [[104.0, 179.0], [190.0, 179.0], [190.0, 363.0], [104.0, 363.0]]], "lines": ["．．．", "おおー"]}, {"box": [1199, 1096, 1313, 1254], "vertical": true, "font_size": 54, "lines_coords": [[[1265.0, 1100.0], [1312.0, 1100.0], [1312.0, 1247.0], [1265.0, 1247.0]], [[1199.0, 1096.0], [1261.0, 1096.0], [1261.0, 1254.0], [1199.0, 1254.0]]], "lines": ["やる！", "やる！"]}, {"box": [959, 1100, 1077, 1299], "vertical": true, "font_size": 54, "lines_coords": [[[1023.0, 1102.0], [1077.0, 1102.0], [1073.0, 1299.0], [1019.0, 1299.0]], [[964.0, 1100.0], [1017.0, 1102.0], [1013.0, 1254.0], [959.0, 1252.0]]], "lines": ["よつばも", "やる！！"]}, {"box": [707, 1119, 765, 1211], "vertical": true, "font_size": 58, "lines_coords": [[[707.0, 1119.0], [765.0, 1119.0], [765.0, 1211.0], [707.0, 1211.0]]], "lines": ["はい"]}, {"box": [619, 1604, 752, 1833], "vertical": true, "font_size": 66, "lines_coords": [[[681.0, 1604.0], [752.0, 1604.0], [752.0, 1777.0], [681.0, 1777.0]], [[619.0, 1611.0], [679.0, 1611.0], [679.0, 1833.0], [619.0, 1833.0]]], "lines": ["おして", "おして！！"]}, {"box": [156, 1619, 193, 1752], "vertical": true, "font_size": 36, "lines_coords": [[[156.0, 1619.0], [192.0, 1619.0], [192.0, 1752.0], [156.0, 1752.0]]], "lines": ["はいはい"]}]}