{"version": "0.2.4", "img_width": 1505, "img_height": 2188, "blocks": [{"box": [1278, 181, 1327, 431], "vertical": true, "font_size": 42, "lines_coords": [[[1282.0, 181.0], [1327.0, 181.0], [1323.0, 431.0], [1278.0, 431.0]]], "lines": ["そりゃ助かる"]}, {"box": [1115, 286, 1252, 564], "vertical": true, "font_size": 42, "lines_coords": [[[1199.0, 286.0], [1252.0, 286.0], [1252.0, 405.0], [1199.0, 405.0]], [[1152.0, 294.0], [1190.0, 294.0], [1192.0, 564.0], [1154.0, 564.0]], [[1115.0, 294.0], [1145.0, 294.0], [1145.0, 499.0], [1115.0, 499.0]]], "lines": ["よっぱ", "お姉ちゃんテレビ", "くれるって！"]}, {"box": [724, 106, 797, 504], "vertical": true, "font_size": 73, "lines_coords": [[[724.0, 106.0], [797.0, 106.0], [797.0, 504.0], [724.0, 504.0]]], "lines": ["やさしいー！！"]}, {"box": [538, 138, 632, 461], "vertical": true, "font_size": 41, "lines_coords": [[[585.0, 138.0], [628.0, 138.0], [628.0, 461.0], [585.0, 461.0]], [[538.0, 138.0], [577.0, 138.0], [577.0, 344.0], [538.0, 344.0]]], "lines": ["アイスクリームも", "くれるか！？"]}, {"box": [132, 589, 212, 805], "vertical": true, "font_size": 30, "lines_coords": [[[177.0, 589.0], [207.0, 589.0], [207.0, 803.0], [177.0, 803.0]], [[132.0, 589.0], [162.0, 589.0], [162.0, 724.0], [132.0, 724.0]]], "lines": ["まぁあったら", "あげるよ"]}, {"box": [168, 1260, 214, 1506], "vertical": true, "font_size": 43, "lines_coords": [[[168.0, 1260.0], [211.0, 1260.0], [211.0, 1506.0], [168.0, 1506.0]]], "lines": ["よかったなぁ"]}, {"box": [557, 1647, 652, 1854], "vertical": true, "font_size": 37, "lines_coords": [[[613.0, 1647.0], [652.0, 1647.0], [647.0, 1854.0], [609.0, 1854.0]], [[562.0, 1649.0], [598.0, 1649.0], [594.0, 1822.0], [557.0, 1822.0]]], "lines": ["じゃあ取りに", "行きます？"]}, {"box": [459, 1728, 502, 2004], "vertical": true, "font_size": 37, "lines_coords": [[[466.0, 1728.0], [502.0, 1728.0], [495.0, 2004.0], [459.0, 2004.0]]], "lines": ["すぐ渡せますけど"]}]}