{"version": "0.2.4", "img_width": 1505, "img_height": 2188, "blocks": [{"box": [1274, 170, 1361, 438], "vertical": true, "font_size": 33, "lines_coords": [[[1325.0, 170.0], [1361.0, 170.0], [1361.0, 309.0], [1325.0, 309.0]], [[1274.0, 173.0], [1304.0, 173.0], [1304.0, 435.0], [1274.0, 435.0]]], "lines": ["そっかー", "よつばの友達がお"]}, {"box": [861, 164, 930, 491], "vertical": true, "font_size": 66, "lines_coords": [[[861.0, 164.0], [927.0, 164.0], [927.0, 491.0], [861.0, 491.0]]], "lines": ["ふーかだ！！"]}, {"box": [348, 412, 442, 617], "vertical": true, "font_size": 34, "lines_coords": [[[384.0, 412.0], [423.0, 412.0], [427.0, 617.0], [389.0, 617.0]], [[348.0, 416.0], [378.0, 416.0], [378.0, 585.0], [348.0, 585.0]]], "lines": ["綾瀬風香です", "よろしくー"]}, {"box": [1344, 794, 1423, 1198], "vertical": true, "font_size": 75, "lines_coords": [[[1348.0, 794.0], [1423.0, 794.0], [1419.0, 1198.0], [1344.0, 1198.0]]], "lines": ["ジャンボだ！！"]}, {"box": [739, 807, 835, 1051], "vertical": true, "font_size": 40, "lines_coords": [[[793.0, 807.0], [835.0, 807.0], [835.0, 1051.0], [793.0, 1051.0]], [[739.0, 807.0], [778.0, 807.0], [778.0, 967.0], [739.0, 967.0]]], "lines": ["ジャンボです", "よろしく"]}, {"box": [551, 866, 583, 1036], "vertical": true, "font_size": 30, "lines_coords": [[[551.0, 867.0], [581.0, 867.0], [581.0, 1034.0], [551.0, 1034.0]]], "lines": ["よろしく．．．"]}, {"box": [1319, 1444, 1410, 1786], "vertical": true, "font_size": 39, "lines_coords": [[[1368.0, 1444.0], [1410.0, 1444.0], [1410.0, 1786.0], [1368.0, 1786.0]], [[1319.0, 1444.0], [1351.0, 1444.0], [1353.0, 1681.0], [1321.0, 1681.0]]], "lines": ["しかしこんな美少女と", "友達になるとは"]}, {"box": [513, 1104, 581, 1328], "vertical": true, "font_size": 31, "lines_coords": [[[530.0, 1108.0], [562.0, 1104.0], [581.0, 1260.0], [549.0, 1264.0]], [[513.0, 1181.0], [542.0, 1179.0], [551.0, 1320.0], [521.0, 1322.0]]], "lines": ["それ名前じゃ", "ないだろう．．"]}, {"box": [634, 1445, 731, 1711], "vertical": true, "font_size": 94, "lines_coords": [[[637.0, 1446.0], [731.0, 1446.0], [731.0, 1664.0], [637.0, 1664.0]]], "lines": ["やーん"]}, {"box": [489, 1495, 573, 1767], "vertical": true, "font_size": 36, "lines_coords": [[[534.0, 1497.0], [570.0, 1497.0], [572.0, 1767.0], [536.0, 1767.0]], [[489.0, 1495.0], [525.0, 1495.0], [525.0, 1634.0], [489.0, 1634.0]]], "lines": ["ビミョーニョって", "なんだ？"]}, {"box": [203, 1425, 295, 1694], "vertical": true, "font_size": 36, "lines_coords": [[[254.0, 1425.0], [290.0, 1425.0], [292.0, 1694.0], [256.0, 1694.0]], [[203.0, 1429.0], [239.0, 1429.0], [239.0, 1564.0], [203.0, 1564.0]]], "lines": ["ビミョーじゃない", "美少女だ"]}, {"box": [1224, 1688, 1267, 1931], "vertical": true, "font_size": 39, "lines_coords": [[[1224.0, 1688.0], [1267.0, 1688.0], [1267.0, 1931.0], [1224.0, 1931.0]]], "lines": ["えらいぞ！"]}]}