{"version": "0.2.4", "img_width": 764, "img_height": 1200, "blocks": [{"box": [597, 117, 684, 189], "vertical": true, "font_size": 32, "lines_coords": [[[644.0, 118.0], [679.0, 117.0], [681.0, 188.0], [646.0, 189.0]], [[617.0, 119.0], [652.0, 119.0], [652.0, 172.0], [617.0, 172.0]], [[597.0, 120.0], [623.0, 120.0], [623.0, 187.0], [597.0, 187.0]]], "lines": ["その人ごうち", "強盗", "よっ！！"]}, {"box": [120, 118, 254, 205], "vertical": true, "font_size": 29, "lines_coords": [[[228.0, 124.0], [254.0, 124.0], [254.0, 194.0], [228.0, 194.0]], [[202.0, 124.0], [228.0, 124.0], [228.0, 188.0], [202.0, 188.0]], [[168.0, 118.0], [207.0, 118.0], [207.0, 172.0], [168.0, 172.0]], [[149.0, 125.0], [171.0, 125.0], [171.0, 205.0], [149.0, 205.0]], [[120.0, 120.0], [151.0, 120.0], [151.0, 159.0], [120.0, 159.0]]], "lines": ["そうだ、", "おれは", "強盗", "だったん", "だ。"]}, {"box": [363, 369, 471, 452], "vertical": true, "font_size": 28, "lines_coords": [[[439.0, 371.0], [471.0, 371.0], [471.0, 438.0], [439.0, 438.0]], [[410.0, 370.0], [442.0, 370.0], [442.0, 420.0], [410.0, 420.0]], [[389.0, 372.0], [410.0, 372.0], [410.0, 452.0], [389.0, 452.0]], [[363.0, 369.0], [391.0, 369.0], [391.0, 408.0], [363.0, 408.0]]], "lines": ["おれの", "お金", "あげます", "よ。"]}, {"box": [120, 373, 193, 458], "vertical": true, "font_size": 23, "lines_coords": [[[168.0, 375.0], [193.0, 375.0], [193.0, 458.0], [168.0, 458.0]], [[144.0, 376.0], [168.0, 376.0], [168.0, 458.0], [144.0, 458.0]], [[120.0, 373.0], [141.0, 373.0], [141.0, 442.0], [120.0, 442.0]]], "lines": ["ほかにも", "いろいろ", "あげる"]}, {"box": [471, 629, 542, 720], "vertical": true, "font_size": 24, "lines_coords": [[[517.0, 629.0], [542.0, 629.0], [542.0, 712.0], [517.0, 712.0]], [[490.0, 630.0], [520.0, 630.0], [520.0, 696.0], [490.0, 696.0]], [[472.0, 632.0], [488.0, 632.0], [488.0, 720.0], [472.0, 720.0]]], "lines": ["まずい！", "つばが", "たまった。"]}, {"box": [357, 624, 412, 720], "vertical": true, "font_size": 26, "lines_coords": [[[387.0, 625.0], [412.0, 625.0], [412.0, 720.0], [387.0, 720.0]], [[357.0, 624.0], [385.0, 624.0], [385.0, 675.0], [357.0, 675.0]]], "lines": ["このやろ", "う！！"]}, {"box": [199, 628, 239, 703], "vertical": true, "font_size": 40, "lines_coords": [[[199.0, 628.0], [239.0, 628.0], [239.0, 703.0], [199.0, 703.0]]], "lines": ["いく"]}, {"box": [168, 869, 297, 939], "vertical": true, "font_size": 30, "lines_coords": [[[265.0, 871.0], [297.0, 871.0], [297.0, 938.0], [265.0, 938.0]], [[242.0, 873.0], [273.0, 873.0], [273.0, 939.0], [242.0, 939.0]], [[216.0, 870.0], [249.0, 870.0], [249.0, 919.0], [216.0, 919.0]], [[192.0, 869.0], [223.0, 869.0], [223.0, 921.0], [192.0, 921.0]], [[168.0, 870.0], [193.0, 870.0], [193.0, 936.0], [168.0, 936.0]]], "lines": ["おれを", "つかま", "えて", "くだ", "さあい"]}]}