{"version": "0.2.4", "img_width": 764, "img_height": 1200, "blocks": [{"box": [413, 122, 438, 208], "vertical": true, "font_size": 25, "lines_coords": [[[413.0, 123.0], [438.0, 123.0], [438.0, 208.0], [413.0, 208.0]]], "lines": ["あった。"]}, {"box": [257, 117, 350, 207], "vertical": true, "font_size": 21, "lines_coords": [[[331.0, 118.0], [348.0, 118.0], [348.0, 207.0], [331.0, 207.0]], [[305.0, 117.0], [326.0, 117.0], [326.0, 175.0], [305.0, 175.0]], [[282.0, 117.0], [302.0, 117.0], [302.0, 194.0], [282.0, 194.0]], [[257.0, 117.0], [282.0, 117.0], [282.0, 183.0], [257.0, 183.0]]], "lines": ["なにもかも", "もとに", "もどして", "おくれ。"]}, {"box": [57, 76, 199, 99], "vertical": false, "font_size": 23, "lines_coords": [[[57.0, 76.0], [199.0, 76.0], [199.0, 99.0], [57.0, 99.0]]], "lines": ["ドラえもん口"]}, {"box": [110, 124, 215, 210], "vertical": true, "font_size": 28, "lines_coords": [[[182.0, 125.0], [213.0, 124.0], [215.0, 180.0], [185.0, 181.0]], [[161.0, 128.0], [186.0, 128.0], [186.0, 210.0], [161.0, 210.0]], [[133.0, 125.0], [162.0, 125.0], [162.0, 194.0], [133.0, 194.0]], [[110.0, 126.0], [137.0, 126.0], [137.0, 181.0], [110.0, 181.0]]], "lines": ["えっ、", "いまさら", "こまり", "ます。"]}, {"box": [538, 365, 704, 580], "vertical": true, "font_size": 25, "lines_coords": [[[674.0, 366.0], [704.0, 366.0], [704.0, 433.0], [674.0, 433.0]], [[644.0, 366.0], [669.0, 366.0], [671.0, 471.0], [646.0, 471.0]], [[619.0, 365.0], [649.0, 366.0], [646.0, 441.0], [617.0, 440.0]], [[592.0, 369.0], [614.0, 369.0], [614.0, 469.0], [592.0, 469.0]], [[568.0, 366.0], [589.0, 366.0], [589.0, 453.0], [568.0, 453.0]], [[540.0, 370.0], [560.0, 370.0], [558.0, 580.0], [539.0, 580.0]]], "lines": ["みんな", "売れちゃい", "ました。", "買いもどす", "にしても", "一週間ほどかかります。"]}, {"box": [408, 367, 501, 465], "vertical": true, "font_size": 24, "lines_coords": [[[481.0, 372.0], [501.0, 372.0], [501.0, 448.0], [481.0, 448.0]], [[453.0, 367.0], [482.0, 367.0], [482.0, 433.0], [453.0, 433.0]], [[434.0, 371.0], [454.0, 371.0], [454.0, 465.0], [434.0, 465.0]], [[408.0, 369.0], [433.0, 369.0], [433.0, 440.0], [408.0, 440.0]]], "lines": ["こまるよ", "はやく", "なんとか", "してよ。"]}, {"box": [162, 371, 294, 441], "vertical": true, "font_size": 29, "lines_coords": [[[258.0, 375.0], [290.0, 375.0], [290.0, 439.0], [258.0, 439.0]], [[236.0, 375.0], [262.0, 375.0], [262.0, 440.0], [236.0, 440.0]], [[208.0, 371.0], [241.0, 371.0], [241.0, 424.0], [208.0, 424.0]], [[185.0, 375.0], [214.0, 375.0], [214.0, 440.0], [185.0, 440.0]], [[162.0, 376.0], [187.0, 376.0], [187.0, 440.0], [162.0, 440.0]]], "lines": ["新しい", "ものは", "すぐ", "そろい", "ますが"]}, {"box": [63, 379, 139, 506], "vertical": true, "font_size": 20, "lines_coords": [[[112.0, 379.0], [137.0, 379.0], [139.0, 465.0], [114.0, 465.0]], [[85.0, 383.0], [105.0, 383.0], [105.0, 485.0], [85.0, 485.0]], [[63.0, 384.0], [79.0, 384.0], [79.0, 505.0], [63.0, 505.0]]], "lines": ["とびきり", "新しいのと", "こうかんして。"]}, {"box": [541, 622, 630, 737], "vertical": true, "font_size": 27, "lines_coords": [[[604.0, 623.0], [630.0, 623.0], [630.0, 696.0], [604.0, 696.0]], [[571.0, 623.0], [596.0, 623.0], [596.0, 737.0], [571.0, 737.0]], [[541.0, 622.0], [571.0, 622.0], [571.0, 684.0], [541.0, 684.0]]], "lines": ["どうも", "落ちつかん", "なあ。"]}, {"box": [94, 629, 206, 799], "vertical": true, "font_size": 24, "lines_coords": [[[180.0, 632.0], [205.0, 632.0], [205.0, 731.0], [180.0, 731.0]], [[152.0, 630.0], [178.0, 631.0], [175.0, 701.0], [149.0, 700.0]], [[125.0, 630.0], [148.0, 630.0], [148.0, 757.0], [125.0, 757.0]], [[94.0, 629.0], [118.0, 629.0], [120.0, 799.0], [97.0, 799.0]]], "lines": ["やっぱり、", "もとに", "もどしてよ。", "なるべくはやく。"]}]}