{"version": "0.2.4", "img_width": 764, "img_height": 1200, "blocks": [{"box": [56, 76, 202, 99], "vertical": false, "font_size": 23, "lines_coords": [[[56.0, 76.0], [202.0, 76.0], [202.0, 99.0], [56.0, 99.0]]], "lines": ["ドラえもんの"]}, {"box": [608, 480, 683, 601], "vertical": true, "font_size": 68, "lines_coords": [[[615.0, 480.0], [683.0, 485.0], [676.0, 601.0], [608.0, 597.0]]], "lines": ["バフッ"]}, {"box": [482, 376, 533, 468], "vertical": true, "font_size": 48, "lines_coords": [[[485.0, 376.0], [533.0, 377.0], [530.0, 468.0], [482.0, 467.0]]], "lines": ["バフッ"]}, {"box": [71, 373, 151, 571], "vertical": true, "font_size": 24, "lines_coords": [[[124.0, 373.0], [148.0, 373.0], [151.0, 471.0], [126.0, 471.0]], [[99.0, 373.0], [123.0, 373.0], [124.0, 571.0], [100.0, 571.0]], [[71.0, 375.0], [94.0, 375.0], [97.0, 537.0], [73.0, 537.0]]], "lines": ["やあやあ、", "おれんちへこいよ！", "だいじにするぜ。"]}, {"box": [625, 622, 710, 737], "vertical": true, "font_size": 26, "lines_coords": [[[680.0, 622.0], [710.0, 622.0], [710.0, 696.0], [680.0, 696.0]], [[655.0, 622.0], [679.0, 622.0], [677.0, 737.0], [652.0, 737.0]], [[625.0, 623.0], [650.0, 623.0], [650.0, 694.0], [625.0, 694.0]]], "lines": ["ぼくの", "「ウマタケ」", "だよ！！"]}, {"box": [386, 619, 482, 713], "vertical": true, "font_size": 20, "lines_coords": [[[453.0, 619.0], [473.0, 619.0], [475.0, 713.0], [455.0, 713.0]], [[431.0, 622.0], [452.0, 622.0], [452.0, 685.0], [431.0, 685.0]], [[408.0, 622.0], [428.0, 622.0], [428.0, 698.0], [408.0, 698.0]], [[387.0, 623.0], [404.0, 623.0], [404.0, 704.0], [387.0, 704.0]]], "lines": ["逃げちゃっ", "たもの、", "しようが", "ないだろ。"]}, {"box": [131, 614, 298, 696], "vertical": true, "font_size": 27, "lines_coords": [[[274.0, 621.0], [298.0, 621.0], [298.0, 682.0], [274.0, 682.0]], [[253.0, 622.0], [274.0, 622.0], [274.0, 696.0], [253.0, 696.0]], [[227.0, 619.0], [254.0, 619.0], [254.0, 672.0], [227.0, 672.0]], [[198.0, 614.0], [233.0, 618.0], [227.0, 665.0], [192.0, 660.0]], [[175.0, 618.0], [203.0, 618.0], [203.0, 664.0], [175.0, 664.0]], [[151.0, 619.0], [180.0, 619.0], [180.0, 684.0], [151.0, 684.0]], [[131.0, 622.0], [153.0, 622.0], [153.0, 679.0], [131.0, 679.0]]], "lines": ["あんな", "あぶない", "もの、", "飼っ", "ちゃ", "いけま", "せん！！"]}, {"box": [495, 873, 594, 956], "vertical": true, "font_size": 26, "lines_coords": [[[569.0, 874.0], [594.0, 874.0], [594.0, 944.0], [569.0, 944.0]], [[546.0, 876.0], [567.0, 876.0], [567.0, 956.0], [546.0, 956.0]], [[516.0, 874.0], [547.0, 874.0], [547.0, 938.0], [516.0, 938.0]], [[495.0, 873.0], [520.0, 873.0], [520.0, 945.0], [495.0, 945.0]]], "lines": ["あした、", "みんなに", "バカに", "される。"]}, {"box": [250, 876, 355, 952], "vertical": true, "font_size": 32, "lines_coords": [[[318.0, 876.0], [355.0, 876.0], [355.0, 936.0], [318.0, 936.0]], [[295.0, 877.0], [331.0, 877.0], [331.0, 945.0], [295.0, 945.0]], [[273.0, 876.0], [302.0, 876.0], [302.0, 941.0], [273.0, 941.0]], [[250.0, 877.0], [275.0, 877.0], [275.0, 952.0], [250.0, 952.0]]], "lines": ["いや、", "これで", "よかっ", "たんだ。"]}, {"box": [71, 873, 206, 984], "vertical": true, "font_size": 22, "lines_coords": [[[176.0, 873.0], [206.0, 873.0], [206.0, 942.0], [176.0, 942.0]], [[151.0, 876.0], [171.0, 876.0], [171.0, 977.0], [151.0, 977.0]], [[125.0, 875.0], [146.0, 875.0], [146.0, 955.0], [125.0, 955.0]], [[99.0, 875.0], [120.0, 875.0], [120.0, 976.0], [99.0, 976.0]], [[71.0, 875.0], [91.0, 875.0], [91.0, 984.0], [71.0, 984.0]]], "lines": ["やはり、", "乗るんなら", "ほんとの", "タケウマに", "乗るべきだ。"]}]}