{"version": "0.2.4", "img_width": 686, "img_height": 1024, "blocks": [{"box": [443, 78, 492, 96], "vertical": false, "font_size": 18, "lines_coords": [[[443.0, 78.0], [492.0, 78.0], [492.0, 96.0], [443.0, 96.0]]], "lines": ["はあ．．．"]}, {"box": [271, 235, 370, 278], "vertical": false, "font_size": 22, "lines_coords": [[[271.0, 236.0], [323.0, 236.0], [323.0, 262.0], [271.0, 262.0]], [[276.0, 261.0], [369.0, 261.0], [369.0, 278.0], [276.0, 278.0]]], "lines": ["行って", "らっしゃい．．．"]}, {"box": [60, 477, 108, 499], "vertical": false, "font_size": 22, "lines_coords": [[[60.0, 477.0], [108.0, 477.0], [108.0, 499.0], [60.0, 499.0]]], "lines": ["わッ！"]}, {"box": [550, 612, 628, 629], "vertical": false, "font_size": 14, "lines_coords": [[[553.0, 614.0], [626.0, 614.0], [626.0, 628.0], [553.0, 628.0]]], "lines": ["それでサー"]}, {"box": [64, 618, 147, 643], "vertical": false, "font_size": 21, "lines_coords": [[[65.0, 622.0], [145.0, 622.0], [145.0, 643.0], [65.0, 643.0]]], "lines": ["入れない．．．"]}, {"box": [488, 889, 586, 927], "vertical": false, "font_size": 16, "lines_coords": [[[491.0, 890.0], [561.0, 890.0], [561.0, 908.0], [491.0, 908.0]], [[492.0, 912.0], [585.0, 912.0], [585.0, 926.0], [492.0, 926.0]]], "lines": ["ボクこう", "いったワケよ"]}]}